rhit/__init__.py
rhit/vilo.py
rhit-0.1.0.dist-info/licenses/LICENSE
rhit-0.1.0.dist-info/METADATA
rhit-0.1.0.dist-info/WHEEL
rhit-0.1.0.dist-info/top_level.txt
rhit-0.1.0.dist-info/RECORD
